simplethoth/__init__.py
simplethoth/scenario.py
simplethoth/app/__init__.py
simplethoth/transcript/__init__.py
simplethoth/transcript/__main__.py
simplethoth/transcript/errors.py
simplethoth/transcript/states.py
simplethoth/transcript/transcripter.py
simplethoth/utils/__init__.py
simplethoth/utils/dict.py
simplethoth-0.1.5.dist-info/METADATA
simplethoth-0.1.5.dist-info/WHEEL
simplethoth-0.1.5.dist-info/top_level.txt
simplethoth-0.1.5.dist-info/RECORD
