Metadata-Version: 2.1
Name: simplethoth
Version: 0.1.5
Summary: UNKNOWN
Home-page: https://github.com/GBS-Skile/SimpleThoth
Author: Jeongmin Lee (Skile)
Author-email: imleejm@gmail.com
License: UNKNOWN
Platform: UNKNOWN
Requires-Python: >=3
Requires-Dist: flask
